LICENSE
README.md
setup.py
TechBook.egg-info/PKG-INFO
TechBook.egg-info/SOURCES.txt
TechBook.egg-info/dependency_links.txt
TechBook.egg-info/not-zip-safe
TechBook.egg-info/top_level.txt
TechBook/CrypticItems/__init__.py
TechBook/CrypticItems/encoders.py
TechBook/CrypticItems/tools.py
TechBook/FileSystemMagic/__init__.py
TechBook/FileSystemMagic/tools.py
TechBook/NetworkConjuration/__init__.py
TechBook/NetworkConjuration/interpreter.py
TechBook/NetworkConjuration/listener.py
TechBook/NetworkConjuration/reverse_shell.py
TechBook/NetworkConjuration/tools.py