Metadata-Version: 2.1
Name: TechBook
Version: 0.0.8
Summary: Spellbook for coders.
Home-page: https://github.com/ClutchTech/TechBook
Author: Clutch_Reboot
Author-email: clutchshadow26@gmail.com
License: GNU General Public License v3.0
Keywords: techbook encoders tools
Platform: UNKNOWN
Requires-Python: >=3.10
License-File: LICENSE
